odoo/addons/report_async/README.rst
odoo/addons/report_async/__init__.py
odoo/addons/report_async/__manifest__.py
odoo/addons/report_async/data/mail_template.xml
odoo/addons/report_async/data/queue_job_function_data.xml
odoo/addons/report_async/demo/report_async_demo.xml
odoo/addons/report_async/i18n/es.po
odoo/addons/report_async/i18n/it.po
odoo/addons/report_async/i18n/report_async.pot
odoo/addons/report_async/models/__init__.py
odoo/addons/report_async/models/ir_actions.py
odoo/addons/report_async/models/ir_report.py
odoo/addons/report_async/models/report_async.py
odoo/addons/report_async/readme/CONTRIBUTORS.md
odoo/addons/report_async/readme/DESCRIPTION.md
odoo/addons/report_async/readme/USAGE.md
odoo/addons/report_async/security/ir.model.access.csv
odoo/addons/report_async/security/ir_rule.xml
odoo/addons/report_async/static/description/icon.png
odoo/addons/report_async/static/description/index.html
odoo/addons/report_async/tests/__init__.py
odoo/addons/report_async/tests/test_report_async.py
odoo/addons/report_async/views/report_async.xml
odoo/addons/report_async/wizard/__init__.py
odoo/addons/report_async/wizard/print_report_wizard.py
odoo/addons/report_async/wizard/print_report_wizard.xml
odoo_addon_report_async-17.0.1.0.0.4.dist-info/METADATA
odoo_addon_report_async-17.0.1.0.0.4.dist-info/WHEEL
odoo_addon_report_async-17.0.1.0.0.4.dist-info/top_level.txt
odoo_addon_report_async-17.0.1.0.0.4.dist-info/RECORD
